pylibjpeg_rle-2.2.0.dist-info/METADATA
pylibjpeg_rle-2.2.0.dist-info/WHEEL
pylibjpeg_rle-2.2.0.dist-info/entry_points.txt
pylibjpeg_rle-2.2.0.dist-info/licenses/LICENSE
rle/__init__.py
rle/_version.py
rle/benchmarks/__init__.py
rle/benchmarks/bench_decode.py
rle/benchmarks/bench_encode.py
rle/py.typed
rle/rle.cp313-win32.pyd
rle/tests/__init__.py
rle/tests/test_decode.py
rle/tests/test_encode.py
rle/tests/test_handler.py
rle/tests/test_utils.py
rle/utils.py
pylibjpeg_rle-2.2.0.dist-info/RECORD
