Metadata-Version: 2.4
Name: pylibjpeg-rle
Version: 2.2.0
Classifier: License :: OSI Approved :: MIT License
Classifier: Intended Audience :: Developers
Classifier: Intended Audience :: Healthcare Industry
Classifier: Intended Audience :: Science/Research
Classifier: Development Status :: 5 - Production/Stable
Classifier: Natural Language :: English
Classifier: Programming Language :: Rust
Classifier: Programming Language :: Python :: 3.10
Classifier: Programming Language :: Python :: 3.11
Classifier: Programming Language :: Python :: 3.12
Classifier: Programming Language :: Python :: 3.13
Classifier: Programming Language :: Python :: 3.14
Classifier: Operating System :: MacOS :: MacOS X
Classifier: Operating System :: POSIX :: Linux
Classifier: Operating System :: Microsoft :: Windows
Classifier: Topic :: Scientific/Engineering :: Medical Science Apps.
Classifier: Topic :: Software Development :: Libraries
Requires-Dist: numpy>=2.0
Requires-Dist: pytest==8.3.5 ; extra == 'test'
Requires-Dist: pydicom>=3.0 ; extra == 'test'
Provides-Extra: test
License-File: LICENSE
Summary: Python bindings for a fast RLE decoder/encoder, with a focus on use as a plugin for pylibjpeg
Keywords: dicom pydicom python rle pylibjpeg rust
Author: pylibjpeg-rle contributors
License-Expression: MIT
Requires-Python: >=3.10
Project-URL: homepage, https://github.com/pydicom/pylibjpeg-rle
